README.md
setup.py
narrenschiff/__init__.py
narrenschiff/autocomplete.py
narrenschiff/chest.py
narrenschiff/common.py
narrenschiff/config.py
narrenschiff/log.py
narrenschiff/narrenschiff.py
narrenschiff/secretmap.py
narrenschiff/task.py
narrenschiff/templating.py
narrenschiff.egg-info/PKG-INFO
narrenschiff.egg-info/SOURCES.txt
narrenschiff.egg-info/dependency_links.txt
narrenschiff.egg-info/entry_points.txt
narrenschiff.egg-info/requires.txt
narrenschiff.egg-info/top_level.txt
narrenschiff/cli/__init__.py
narrenschiff/cli/autocomplete.py
narrenschiff/cli/chest.py
narrenschiff/cli/dock.py
narrenschiff/cli/env.py
narrenschiff/cli/lint.py
narrenschiff/cli/sail.py
narrenschiff/cli/secretmap.py
narrenschiff/filters/__init__.py
narrenschiff/modules/__init__.py
narrenschiff/modules/common.py
narrenschiff/modules/gcloud.py
narrenschiff/modules/helm.py
narrenschiff/modules/kubectl.py
narrenschiff/modules/kustomization.py
narrenschiff/modules/mixins.py
narrenschiff/modules/wait_for_pod.py