Metadata-Version: 2.1
Name: narrenschiff
Version: 3.4.3
Summary: Configuration management tool for Kubernetes
Home-page: https://narrenschiff.xyz
Maintainer: Petar Nikolovski
Maintainer-email: petar.nikolovski@protonmail.com
License: Apache License, Version 2.0
Project-URL: Documentation, https://docs.narrenschiff.xyz
Project-URL: Source, https://github.com/narrenorg/narrenschiff
Platform: UNKNOWN
Classifier: Environment :: Console
Classifier: Development Status :: 4 - Beta
Classifier: Intended Audience :: Developers
Classifier: License :: OSI Approved :: Apache Software License
Classifier: Programming Language :: Python :: 3
Classifier: Programming Language :: Python :: 3.6
Classifier: Operating System :: POSIX
Classifier: Topic :: Utilities
